Workbook

Sheet Ringkasan
B2: SCORING ANALISA KREDIT PENDIDIKAN
B3: Calon siswa: Paridudin | Amaterasu Japanese School
B6: HASIL UTAMA
B7: Parameter | C7: Hasil
B8: Skor kelayakan calon siswa (Lendana) | C8: 97.4
B9: Skor kredit berbasis RC keluarga | C9: ='Scoring Kredit'!G29 -> 80
B10: Critical gate belum terpenuhi | C10: =COUNTIF('Scoring Kredit'!I6:I28,"FAIL") -> 0
B11: Rekomendasi | C11: =IF(C10>0,"TUNDA - CRITICAL GATE BELUM TERPENUHI",IF(C9>=80,"LAYAK DIREKOMENDASIKAN",IF(C9>=70,"DIPERTIMBANGKAN KOMITE","TIDAK DIREKOMENDASIKAN"))) -> LAYAK DIREKOMENDASIKAN
B14: KESIMPULAN ANALISA
B15: Skor 97,4 dari Lendana menunjukkan kelayakan calon siswa, bukan kemampuan membayar kredit. Data yang tersedia belum membuktikan penghasilan, pengeluaran, kewajiban dan kemampuan bayar ibu/kakak. Karena itu keputusan tetap tertahan sampai seluruh critical gate repayment capacity dipenuhi.
B16: Pihak keluarga yang membayar harus ditetapkan dan diikat sebagai Debitur Bersama yang bertanggung renteng. Rencana bekerja di Jepang, refinancing, asuransi, saldo ditahan dan dukungan LPK hanya merupakan mitigasi atau sumber pembayaran alternatif.
B17: Isi sel berwarna kuning pada sheet RC Keluarga. Skor dan rekomendasi akan berubah otomatis.
B21: CRITICAL GATE
B22: Syarat | C22: Status | D22: Sumber | E22: Tindakan
B23: Pihak pembayar primer teridentifikasi | C23: ='Scoring Kredit'!I15 -> PASS | D23: RC Keluarga | E23: Tentukan ibu/kakak/pihak lain
B24: Penghasilan bersih terverifikasi | C24: ='Scoring Kredit'!I16 -> PASS | D24: RC Keluarga | E24: Lengkapi bukti 6–12 bulan
B25: Pengeluaran dan utang terverifikasi | C25: ='Scoring Kredit'!I17 -> PASS | D25: RC Keluarga | E25: Lengkapi SLIK dan deklarasi utang
B26: DSR memenuhi kebijakan | C26: ='Scoring Kredit'!I18 -> PASS | D26: RC Keluarga | E26: Hitung setelah angka lengkap
B27: Stress test tetap positif | C27: ='Scoring Kredit'!I19 -> PASS | D27: RC Keluarga | E27: Uji penurunan penghasilan 30%
B28: Pemahaman program/dana talang | C28: ='Scoring Kredit'!I21 -> PASS | D28: RC Keluarga | E28: Edukasi ulang dan konfirmasi
B29: Debitur Bersama telah setuju | C29: ='Scoring Kredit'!I24 -> PASS | D29: RC Keluarga | E29: Tanda tangan akad tanggung renteng
B32: Catatan keputusan

Sheet Scoring Kredit
B2: SCORING KREDIT BERBASIS REPAYMENT CAPACITY KELUARGA
B3: Skala 0–5. Nilai 0 berarti data wajib belum tersedia. Nilai minimum critical gate adalah 3.
B5: Kelompok | C5: Kriteria | D5: Bobot | E5: Nilai 0–5 | F5: Dasar penilaian | G5: Skor tertimbang | H5: Critical gate | I5: Status gate
B6: Character & SLIK | C6: Konsistensi identitas dan alamat | D6: 3 | E6: 3 | F6: Identitas cocok; domisili interview Bekasi, alamat SLIK Sukabumi | G6: =D6*E6/5 -> 1.8 | H6: Tidak | I6: =IF(H6="Ya",IF(E6>=3,"PASS","FAIL"),"-") -> -
B7: Character & SLIK | C7: Riwayat pembayaran/SLIK siswa | D7: 5 | E7: 5 | F7: 1 fasilitas BNPL Rp120 ribu, saldo dan tunggakan Rp0 | G7: =D7*E7/5 -> 5 | H7: Tidak | I7: =IF(H7="Ya",IF(E7>=3,"PASS","FAIL"),"-") -> -
B8: Character & SLIK | C8: Keterbukaan informasi dan pemahaman awal | D8: 4 | E8: 2 | F8: Catatan izin keluarga dan pemahaman dana talang belum konsisten | G8: =D8*E8/5 -> 1.6 | H8: Tidak | I8: =IF(H8="Ya",IF(E8>=3,"PASS","FAIL"),"-") -> -
B9: Character & SLIK | C9: Dukungan keluarga yang telah dikonfirmasi | D9: 3 | E9: 1 | F9: Ibu belum dikonfirmasi; kakak disebut masih ragu | G9: =D9*E9/5 -> 0.6 | H9: Tidak | I9: =IF(H9="Ya",IF(E9>=3,"PASS","FAIL"),"-") -> -
B10: Kesiapan siswa | C10: Hasil interview | D10: 4 | E10: 4 | F10: Skor 31 dibanding standar 27; disarankan | G10: =D10*E10/5 -> 3.2 | H10: Tidak | I10: =IF(H10="Ya",IF(E10>=3,"PASS","FAIL"),"-") -> -
B11: Kesiapan siswa | C11: Motivasi dan komitmen | D11: 4 | E11: 4 | F11: Motivasi kuat; keyakinan 95% | G11: =D11*E11/5 -> 3.2 | H11: Tidak | I11: =IF(H11="Ya",IF(E11>=3,"PASS","FAIL"),"-") -> -
B12: Kesiapan siswa | C12: Kemampuan kognitif dan belajar | D12: 4 | E12: 3 | F12: IQ 96; kapasitas rata-rata; perlu pembinaan | G12: =D12*E12/5 -> 2.4 | H12: Tidak | I12: =IF(H12="Ya",IF(E12>=3,"PASS","FAIL"),"-") -> -
B13: Kesiapan siswa | C13: Disiplin, ketekunan dan daya tahan | D13: 5 | E13: 2 | F13: Mudah menyerah, disiplin/tanggung jawab dan stamina rendah | G13: =D13*E13/5 -> 2 | H13: Tidak | I13: =IF(H13="Ya",IF(E13>=3,"PASS","FAIL"),"-") -> -
B14: Kesiapan siswa | C14: Kesehatan untuk bekerja | D14: 3 | E14: 4 | F14: Fit; underweight, anemia ringan dan perawatan gigi perlu tindak lanjut | G14: =D14*E14/5 -> 2.4 | H14: Tidak | I14: =IF(H14="Ya",IF(E14>=3,"PASS","FAIL"),"-") -> -
B15: RC keluarga | C15: Pihak pembayar primer teridentifikasi | D15: 5 | E15: =IF('RC Keluarga'!C19="Ya",5,0) -> 5 | F15: Diambil dari RC Keluarga | G15: =D15*E15/5 -> 5 | H15: Ya | I15: =IF(H15="Ya",IF(E15>=3,"PASS","FAIL"),"-") -> PASS
B16: RC keluarga | C16: Penghasilan bersih terverifikasi | D16: 8 | E16: =IF('RC Keluarga'!C20="Ya",5,0) -> 5 | F16: Diambil dari RC Keluarga | G16: =D16*E16/5 -> 8 | H16: Ya | I16: =IF(H16="Ya",IF(E16>=3,"PASS","FAIL"),"-") -> PASS
B17: RC keluarga | C17: Pengeluaran dan seluruh utang terverifikasi | D17: 6 | E17: =IF('RC Keluarga'!C21="Ya",5,0) -> 5 | F17: Diambil dari RC Keluarga | G17: =D17*E17/5 -> 6 | H17: Ya | I17: =IF(H17="Ya",IF(E17>=3,"PASS","FAIL"),"-") -> PASS
B18: RC keluarga | C18: DSR setelah kredit | D18: 8 | E18: =IF('RC Keluarga'!C11="",0,IF('RC Keluarga'!C11<=35%,5,IF('RC Keluarga'!C11<=40%,4,IF('RC Keluarga'!C11<=45%,3,IF('RC Keluarga'!C11<=50%,2,1))))) -> 5 | F18: Otomatis dari angka RC | G18: =D18*E18/5 -> 8 | H18: Ya | I18: =IF(H18="Ya",IF(E18>=3,"PASS","FAIL"),"-") -> PASS
B19: RC keluarga | C19: Residual income pada stress test | D19: 8 | E19: =IF('RC Keluarga'!C15="",0,IF('RC Keluarga'!C15<=0,1,IF('RC Keluarga'!C15/'RC Keluarga'!C13>=20%,5,IF('RC Keluarga'!C15/'RC Keluarga'!C13>=10%,4,3)))) -> 5 | F19: Otomatis: penghasilan -30%, biaya hidup +10% | G19: =D19*E19/5 -> 8 | H19: Ya | I19: =IF(H19="Ya",IF(E19>=3,"PASS","FAIL"),"-") -> PASS
B20: Program & LPK | C20: Kualitas/rekam jejak LPK | D20: 5 | E20: 5 | F20: Scoring Lendana memberi nilai LPK 25/25 | G20: =D20*E20/5 -> 5 | H20: Tidak | I20: =IF(H20="Ya",IF(E20>=3,"PASS","FAIL"),"-") -> -
B21: Program & LPK | C21: Pemahaman program dan dana talang | D21: 4 | E21: =IF('RC Keluarga'!C23="Ya",5,0) -> 5 | F21: Diambil dari RC Keluarga | G21: =D21*E21/5 -> 4 | H21: Ya | I21: =IF(H21="Ya",IF(E21>=3,"PASS","FAIL"),"-") -> PASS
B22: Program & LPK | C22: Milestone pencairan dan refund | D22: 3 | E22: =IF('RC Keluarga'!C24="Ya",5,0) -> 5 | F22: Diambil dari RC Keluarga | G22: =D22*E22/5 -> 3 | H22: Tidak | I22: =IF(H22="Ya",IF(E22>=3,"PASS","FAIL"),"-") -> -
B23: Program & LPK | C23: Kejelasan penempatan/refinancing | D23: 3 | E23: 2 | F23: Belum ada bukti final dalam berkas kandidat | G23: =D23*E23/5 -> 1.2 | H23: Tidak | I23: =IF(H23="Ya",IF(E23>=3,"PASS","FAIL"),"-") -> -
B24: Struktur & mitigasi | C24: Debitur Bersama/tanggung renteng | D24: 5 | E24: =IF('RC Keluarga'!C22="Ya",5,0) -> 5 | F24: Diambil dari RC Keluarga | G24: =D24*E24/5 -> 5 | H24: Ya | I24: =IF(H24="Ya",IF(E24>=3,"PASS","FAIL"),"-") -> PASS
B25: Struktur & mitigasi | C25: Agunan, asuransi atau dana darurat | D25: 3 | E25: 0 | F25: Belum tersedia dalam berkas kandidat | G25: =D25*E25/5 -> 0 | H25: Tidak | I25: =IF(H25="Ya",IF(E25>=3,"PASS","FAIL"),"-") -> -
B26: Struktur & mitigasi | C26: Pencairan bertahap | D26: 3 | E26: =IF('RC Keluarga'!C25="Ya",5,0) -> 5 | F26: Diambil dari RC Keluarga | G26: =D26*E26/5 -> 3 | H26: Tidak | I26: =IF(H26="Ya",IF(E26>=3,"PASS","FAIL"),"-") -> -
B27: Struktur & mitigasi | C27: Monitoring kemajuan siswa | D27: 2 | E27: 2 | F27: Rekomendasi mentoring tersedia; mekanisme belum final | G27: =D27*E27/5 -> 0.8 | H27: Tidak | I27: =IF(H27="Ya",IF(E27>=3,"PASS","FAIL"),"-") -> -
B28: Struktur & mitigasi | C28: Kelengkapan dokumen kredit | D28: 2 | E28: 2 | F28: Dokumen siswa tersedia; dokumen keluarga belum tersedia | G28: =D28*E28/5 -> 0.8 | H28: Tidak | I28: =IF(H28="Ya",IF(E28>=3,"PASS","FAIL"),"-") -> -
B29: TOTAL | D29: =SUM(D6:D28) -> 100 | G29: =SUM(G6:G28) -> 80
B32: INTERPRETASI SKOR
B33: 80–100 | C33: Layak direkomendasikan jika seluruh critical gate PASS
B34: 70–79,9 | C34: Dipertimbangkan Komite Kredit jika seluruh critical gate PASS
B35: <70 | C35: Tidak direkomendasikan
B36: Critical gate FAIL | C36: Keputusan wajib TUNDA, berapa pun total skor

Sheet RC Keluarga
B2: REPAYMENT CAPACITY ORANG TUA / KELUARGA
B3: Isi sel kuning dengan angka bulanan yang telah diverifikasi. Jangan memasukkan proyeksi gaji Jepang sebagai penghasilan saat ini.
B5: PERHITUNGAN KEMAMPUAN BAYAR
B6: Komponen | C6: Nilai per bulan | D6: Bukti/verifikasi | E6: Keterangan
B7: Penghasilan bersih terverifikasi | C7: 9000000 | D7: Belum tersedia | E7: Rata-rata konservatif 6–12 bulan / satu siklus usaha tani
B8: Biaya hidup rumah tangga | C8: 1000000 | D8: Belum tersedia | E8: Termasuk tanggungan dan kebutuhan dasar
B9: Angsuran kredit berjalan | D9: Belum tersedia | E9: Cocokkan dengan SLIK dan deklarasi utang
B10: Angsuran kredit pendidikan usulan | D10: Belum ditetapkan | E10: Sesuai plafon, bunga dan tenor final
B11: DSR setelah kredit | C11: =IF(C7="","",(C9+C10)/C7) -> 0 | D11: Otomatis | E11: (Angsuran berjalan + angsuran usulan) / penghasilan
B12: Residual income | C12: =IF(C7="","",C7-C8-C9-C10) -> 8000000 | D12: Otomatis | E12: Penghasilan - biaya hidup - seluruh angsuran
B13: Penghasilan stress test (-30%) | C13: =IF(C7="","",C7*70%) -> 6300000 | D13: Otomatis | E13: Skenario konservatif
B14: Biaya hidup stress test (+10%) | C14: =IF(C8="","",C8*110%) -> 1100000 | D14: Otomatis | E14: Skenario konservatif
B15: Residual income stress test | C15: =IF(OR(C13="",C14=""),"",C13-C14-C9-C10) -> 5200000 | D15: Otomatis | E15: Harus tetap positif
B16: DSR stress test | C16: =IF(C13="","",(C9+C10)/C13) -> 0 | D16: Otomatis | E16: Untuk pertimbangan tambahan
B18: CRITICAL GATE DAN DOKUMEN
B19: Pihak pembayar primer telah ditetapkan | C19: Ya | D19: Belum tersedia | E19: Nama dan hubungan: [diisi]
B20: Bukti penghasilan telah diverifikasi | C20: Ya | D20: Belum tersedia | E20: Slip gaji/rekening koran/catatan usaha
B21: Pengeluaran dan seluruh utang telah diverifikasi | C21: Ya | D21: Belum tersedia | E21: SLIK, deklarasi utang, biaya hidup
B22: Debitur Bersama bersedia tanggung renteng | C22: Ya | D22: Belum tersedia | E22: Akad dan persetujuan pasangan bila relevan
B23: Orang tua/siswa memahami program dan dana talang | C23: Ya | D23: Belum tersedia | E23: Edukasi ulang dan konfirmasi tertulis
B24: Tahapan pencairan dan refund telah disepakati | C24: Ya | D24: Belum tersedia | E24: Perjanjian dengan LPK/mitra
B25: Pencairan bertahap telah disetujui | C25: Ya | D25: Belum tersedia | E25: Jadwal tahapan pencairan dan kontrol invoice
B28: PANDUAN PENILAIAN
B29: DSR | C29: 5: ≤35% | 4: >35–40% | 3: >40–45% | 2: >45–50% | 1: >50%
B30: Stress test | C30: 5: residual ≥20% penghasilan stress | 4: ≥10% | 3: positif <10% | 1: negatif
B31: Ketentuan | C31: Batas DSR final mengikuti kebijakan internal BPR. Critical gate minimal bernilai 3.
